NiLBS/__init__.py
NiLBS/main.py
NiLBS/notebook_tools.py
NiLBS/body/__init__.py
NiLBS/body/human_body.py
NiLBS/data/amass_mpi_sample_poses.npz
NiLBS/data/female_body_model_smplh.npz
NiLBS/demo/__init__.py
NiLBS/demo/scene.py
NiLBS/mesh/__init__.py
NiLBS/mesh/mesh_occupancy.py
NiLBS/mesh/voxel_matrix.py
NiLBS/occupancy/__init__.py
NiLBS/occupancy/occupancy_function.py
NiLBS/occupancy/occupancy_function_mesh.py
NiLBS/occupancy/occupancy_function_rest_cached.py
NiLBS/occupancy/occupancy_function_voxel.py
NiLBS/occupancy/winding_numbers.py
NiLBS/occupancy/voxel/__init__.py
NiLBS/occupancy/voxel/util.py
NiLBS/occupancy/voxel/voxel_tree.py
NiLBS/pose/__init__.py
NiLBS/pose/pose.py
NiLBS/pose/util.py
NiLBS/sampling/__init__.py
NiLBS/sampling/point_sampler_box.py
NiLBS/sampling/point_sampler_surface.py
NiLBS/sampling/pose_sampler_amass.py
NiLBS/sampling/weight_train_sampler.py
NiLBS/skinning/__init__.py
NiLBS/skinning/skinning_mesh_lbs.py
NiLBS/skinning/util.py
NiLBS/weighting/__init__.py
NiLBS/weighting/weighting_function.py
NiLBS/weighting/weighting_function_mlp.py
NiLBS/weighting/weighting_function_mlp_naive.py
NiLBS/weighting/weighting_function_mlp_rest_naive.py
NiLBS/weighting/weighting_function_nilbs.py
NiLBS/weighting/weighting_function_pointwise.py
NiLBS-0.5.10.dist-info/LICENSE
NiLBS-0.5.10.dist-info/METADATA
NiLBS-0.5.10.dist-info/WHEEL
NiLBS-0.5.10.dist-info/top_level.txt
NiLBS-0.5.10.dist-info/RECORD
