Metadata-Version: 2.1
Name: NiLBS
Version: 0.5.10
Summary: NiLBS 3D implementation.
Home-page: UNKNOWN
Author: Joe March
Author-email: jgm45@cam.ac.uk
License: UNKNOWN
Platform: UNKNOWN
Requires-Dist: rtree
Requires-Dist: trimesh
Requires-Dist: pyrender
Requires-Dist: tensorflow
